monsoon_crop_predictor/__init__.py
monsoon_crop_predictor/api/__init__.py
monsoon_crop_predictor/api/endpoints.py
monsoon_crop_predictor/api/middleware.py
monsoon_crop_predictor/api/schemas.py
monsoon_crop_predictor/cli/__init__.py
monsoon_crop_predictor/cli/commands.py
monsoon_crop_predictor/core/__init__.py
monsoon_crop_predictor/core/data_loader.py
monsoon_crop_predictor/core/feature_engineer.py
monsoon_crop_predictor/core/predictor.py
monsoon_crop_predictor/core/preprocessor.py
monsoon_crop_predictor/core/validator.py
monsoon_crop_predictor/models/__init__.py
monsoon_crop_predictor/models/ensemble.py
monsoon_crop_predictor/models/best_advanced_models/advanced_feature_analysis.pkl
monsoon_crop_predictor/models/best_advanced_models/maize_best_advanced_ensemble.pkl
monsoon_crop_predictor/models/best_advanced_models/rice_best_advanced_ensemble.pkl
monsoon_crop_predictor/models/best_advanced_models/wheat_best_advanced_ensemble.pkl
monsoon_crop_predictor/utils/__init__.py
monsoon_crop_predictor/utils/config.py
monsoon_crop_predictor/utils/exceptions.py
monsoon_crop_predictor/utils/logger.py
monsoon_crop_predictor-0.1.0.dist-info/licenses/LICENSE
monsoon_crop_predictor-0.1.0.dist-info/METADATA
monsoon_crop_predictor-0.1.0.dist-info/WHEEL
monsoon_crop_predictor-0.1.0.dist-info/entry_points.txt
monsoon_crop_predictor-0.1.0.dist-info/top_level.txt
monsoon_crop_predictor-0.1.0.dist-info/RECORD
