Metadata-Version: 2.4
Name: monsoon-crop-predictor
Version: 0.1.0
Summary: Advanced ML-based crop yield prediction system using monsoon and rainfall data
Home-page: https://github.com/SubratDash67/Monsoon-Crop-Yield
Author: Subrat Dash
Author-email: Subrat Dash <subratdash2022@gmail.com>
License: MIT
Project-URL: Homepage, https://github.com/SubratDash67/Monsoon-Crop-Yield
Project-URL: Documentation, https://github.com/SubratDash67/Monsoon-Crop-Yield/blob/main/README.md
Project-URL: Repository, https://github.com/SubratDash67/Monsoon-Crop-Yield
Project-URL: Bug Tracker, https://github.com/SubratDash67/Monsoon-Crop-Yield/issues
Keywords: agriculture,crop yield,machine learning,monsoon,rainfall,prediction
Classifier: Development Status :: 3 - Alpha
Classifier: Intended Audience :: Science/Research
Classifier: Intended Audience :: Developers
Classifier: Topic :: Scientific/Engineering :: Artificial Intelligence
Classifier: Topic :: Scientific/Engineering :: Atmospheric Science
Classifier: License :: OSI Approved :: MIT License
Classifier: Programming Language :: Python :: 3
Classifier: Programming Language :: Python :: 3.8
Classifier: Programming Language :: Python :: 3.9
Classifier: Programming Language :: Python :: 3.10
Classifier: Programming Language :: Python :: 3.11
Classifier: Operating System :: OS Independent
Requires-Python: >=3.8
License-File: LICENSE
Requires-Dist: numpy>=1.21.0
Requires-Dist: pandas>=1.3.0
Requires-Dist: scikit-learn>=1.0.0
Requires-Dist: scipy>=1.7.0
Requires-Dist: lightgbm>=3.2.0
Requires-Dist: xgboost>=1.4.0
Provides-Extra: api
Requires-Dist: fastapi>=0.68.0; extra == "api"
Requires-Dist: uvicorn[standard]>=0.15.0; extra == "api"
Requires-Dist: pydantic>=1.8.0; extra == "api"
Provides-Extra: cli
Requires-Dist: click>=8.0.0; extra == "cli"
Provides-Extra: visualization
Requires-Dist: matplotlib>=3.3.0; extra == "visualization"
Requires-Dist: seaborn>=0.11.0; extra == "visualization"
Requires-Dist: plotly>=5.0.0; extra == "visualization"
Provides-Extra: jupyter
Requires-Dist: jupyter>=1.0.0; extra == "jupyter"
Requires-Dist: ipykernel>=6.0.0; extra == "jupyter"
Requires-Dist: notebook>=6.4.0; extra == "jupyter"
Provides-Extra: dev
Requires-Dist: pytest>=6.0.0; extra == "dev"
Requires-Dist: pytest-cov>=2.12.0; extra == "dev"
Requires-Dist: black>=21.0.0; extra == "dev"
Requires-Dist: flake8>=3.9.0; extra == "dev"
Requires-Dist: mypy>=0.910; extra == "dev"
Requires-Dist: pre-commit>=2.15.0; extra == "dev"
Provides-Extra: all
Requires-Dist: fastapi>=0.68.0; extra == "all"
Requires-Dist: uvicorn[standard]>=0.15.0; extra == "all"
Requires-Dist: pydantic>=1.8.0; extra == "all"
Requires-Dist: click>=8.0.0; extra == "all"
Requires-Dist: matplotlib>=3.3.0; extra == "all"
Requires-Dist: seaborn>=0.11.0; extra == "all"
Requires-Dist: plotly>=5.0.0; extra == "all"
Requires-Dist: jupyter>=1.0.0; extra == "all"
Requires-Dist: ipykernel>=6.0.0; extra == "all"
Requires-Dist: notebook>=6.4.0; extra == "all"
Dynamic: author
Dynamic: home-page
Dynamic: license-file
Dynamic: requires-python
